Xethru_radar/X4_radar_data_collection.py
Xethru_radar/XEP_X4M200_X4M300_plot_record_playback_radar_raw_data.py
Xethru_radar/__init__.py
Xethru_radar/convertdata2.py
Xethru_radar/data_parser.py
sensor_lib-0.0.4.dist-info/LICENSE.txt
sensor_lib-0.0.4.dist-info/METADATA
sensor_lib-0.0.4.dist-info/WHEEL
sensor_lib-0.0.4.dist-info/top_level.txt
sensor_lib-0.0.4.dist-info/RECORD
